LICENSE
MANIFEST.in
README.rst
setup.cfg
setup.py
audiodatasets/__init__.py
audiodatasets/basecorpus.py
audiodatasets/corpora.py
audiodatasets/librispeech.py
audiodatasets/preprocess.py
audiodatasets/searchwords.py
audiodatasets/tedlium.py
audiodatasets/vctk.py
audiodatasets.egg-info/PKG-INFO
audiodatasets.egg-info/SOURCES.txt
audiodatasets.egg-info/dependency_links.txt
audiodatasets.egg-info/entry_points.txt
audiodatasets.egg-info/not-zip-safe
audiodatasets.egg-info/requires.txt
audiodatasets.egg-info/top_level.txt
docs/Makefile
docs/conf.py
docs/contributing.rst
docs/history.rst
docs/index.rst
docs/installation.rst
docs/make.bat
docs/readme.rst
docs/usage.rst
tests/__init__.py