Metadata-Version: 1.1
Name: audiodatasets
Version: 1.0.0
Summary: Pulls and pre-processes major Open Source (non-commercial mostly) datasets for spoken audio
Home-page: https://github.com/mcfletch/audiodatasets
Author: Mike C. Fletcher
Author-email: mcfletch@vrplumber.com
License: MIT license
Keywords: audiodatasets
Platform: UNKNOWN
Classifier: Intended Audience :: Developers
Classifier: License :: OSI Approved :: MIT License
Classifier: Natural Language :: English
Classifier: Programming Language :: Python :: 2
Classifier: Programming Language :: Python :: 2.6
Classifier: Programming Language :: Python :: 2.7
Classifier: Programming Language :: Python :: 3
Classifier: Programming Language :: Python :: 3.3
Classifier: Programming Language :: Python :: 3.4
Classifier: Programming Language :: Python :: 3.5
